is_natural_number/__init__.py
is_natural_number-1.0.0.dist-info/LICENSE
is_natural_number-1.0.0.dist-info/METADATA
is_natural_number-1.0.0.dist-info/WHEEL
is_natural_number-1.0.0.dist-info/top_level.txt
is_natural_number-1.0.0.dist-info/RECORD
