Metadata-Version: 2.1
Name: is-natural-number
Version: 1.0.0
Summary: Check if a value is a natural number
Home-page: https://github.com/adamzerella/is-natural-number
Author: Adam Zerella
Author-email: hello@adamzerella.com
License: UNKNOWN
Platform: UNKNOWN
Classifier: Programming Language :: Python :: 3
Classifier: License :: OSI Approved :: MIT License
Classifier: Operating System :: OS Independent
